cloudsdp/__init__.py
cloudsdp/api/__init__.py
cloudsdp/api/bigquery.py
cloudsdp/api/cloudrun.py
cloudsdp/utilities.py
cloudsdp-0.1.11.dist-info/LICENSE
cloudsdp-0.1.11.dist-info/METADATA
cloudsdp-0.1.11.dist-info/WHEEL
cloudsdp-0.1.11.dist-info/RECORD
