Metadata-Version: 2.1
Name: cloudsdp
Version: 0.1.11
Summary: 
Home-page: https://github.com/nvn-nil/CloudSDP
Keywords: cloud,data,processing,extraction,transformation,ingestion,ETL,BigQuery,Google Cloud,data pipeline
Author: Naveen Anil
Author-email: naveenms01@gmail.com
Requires-Python: >=3.9,<4.0
Classifier: Programming Language :: Python :: 3
Classifier: Programming Language :: Python :: 3.9
Classifier: Programming Language :: Python :: 3.10
Classifier: Programming Language :: Python :: 3.11
Requires-Dist: deepdiff (>=6.3.1,<7.0.0)
Requires-Dist: google-cloud-bigquery (>=3.11.4,<4.0.0)
Requires-Dist: google-cloud-run (>=0.9.1,<0.10.0)
Requires-Dist: pyarrow (>=12.0.1,<13.0.0)
Project-URL: Documentation, https://nvn-nil.github.io/CloudSDP/
Project-URL: Repository, https://github.com/nvn-nil/CloudSDP
